{
    "id": -1001560588492,
    "name": "English_A-45(IT)_2021/22",
    "type": "Group",
    "users": [
        {
            "user_id": 811199493,
            "first_name": "Jester stickbug",
            "last_name": null,
            "username": "GoshDarn_Brit",
            "phone": null
        },
        {
            "user_id": 296315254,
            "first_name": "Деодат",
            "last_name": null,
            "username": "reactionist",
            "phone": null
        },
        {
            "user_id": 633201121,
            "first_name": "ARINA",
            "last_name": null,
            "username": "darlingvillain",
            "phone": null
        },
        {
            "user_id": 332402450,
            "first_name": "Alex",
            "last_name": "Severgin",
            "username": "just_me_alex",
            "phone": "380964966800"
        },
        {
            "user_id": 98325644,
            "first_name": "Dima",
            "last_name": "Braginets",
            "username": "braginets",
            "phone": null
        },
        {
            "user_id": 642712230,
            "first_name": "Ксеня",
            "last_name": null,
            "username": "xeno_murf",
            "phone": null
        },
        {
            "user_id": 763330259,
            "first_name": "Egor",
            "last_name": "Kirillin",
            "username": "RickNeelee",
            "phone": null
        },
        {
            "user_id": 798852178,
            "first_name": "Федор Андреевич",
            "last_name": null,
            "username": "letaldir",
            "phone": null
        },
        {
            "user_id": 974447018,
            "first_name": "Yuliia",
            "last_name": "Datsko",
            "username": "datulka",
            "phone": "380633033384"
        },
        {
            "user_id": 559072245,
            "first_name": "Катя",
            "last_name": null,
            "username": "luch_ka",
            "phone": null
        },
        {
            "user_id": 497713871,
            "first_name": "Богдан",
            "last_name": "Гурський",
            "username": "Bhurskyy",
            "phone": null
        },
        {
            "user_id": 507584973,
            "first_name": "Дима",
            "last_name": "Пелович",
            "username": "dmeauxn",
            "phone": null
        },
        {
            "user_id": 380133204,
            "first_name": "Pavlo Yashchenko",
            "last_name": null,
            "username": "Lord_4ikkamony",
            "phone": null
        },
        {
            "user_id": 607181631,
            "first_name": "andrii",
            "last_name": "snigir",
            "username": "sniigg",
            "phone": null
        },
        {
            "user_id": 255009795,
            "first_name": "Данило Козак",
            "last_name": null,
            "username": "danylo_kozak",
            "phone": null
        }
    ]
}